spikely/__init__.py
spikely/config.py
spikely/file_menu.py
spikely/guiparams.py
spikely/help_menu.py
spikely/operation_view.py
spikely/parameter_model.py
spikely/parameter_view.py
spikely/pipeline_model.py
spikely/pipeline_view.py
spikely/spikely_main.py
spikely/tool_bar.py
spikely/version.py
spikely/elements/__init__.py
spikely/elements/curator.py
spikely/elements/element_policy.py
spikely/elements/exporter.py
spikely/elements/exporterlist.py
spikely/elements/extractor.py
spikely/elements/phy_exporter.py
spikely/elements/preprocessor.py
spikely/elements/sorter.py
spikely/elements/spike_element.py
spikely/elements/std_element_policy.py
spikely/elements/guiparams/__init__.py
spikely/elements/guiparams/curator/__init__.py
spikely/elements/guiparams/curator/thresholdamplitudecutoffs.py
spikely/elements/guiparams/curator/thresholddprimes.py
spikely/elements/guiparams/curator/thresholddriftmetrics.py
spikely/elements/guiparams/curator/thresholdfiringrates.py
spikely/elements/guiparams/curator/thresholdisiviolations.py
spikely/elements/guiparams/curator/thresholdisolationdistances.py
spikely/elements/guiparams/curator/thresholdlratios.py
spikely/elements/guiparams/curator/thresholdnnmetrics.py
spikely/elements/guiparams/curator/thresholdnumspikes.py
spikely/elements/guiparams/curator/thresholdpresenceratios.py
spikely/elements/guiparams/curator/thresholdsilhouettescores.py
spikely/elements/guiparams/curator/thresholdsnrs.py
spikely/elements/guiparams/exporter/__init__.py
spikely/elements/guiparams/exporter/phyexporter.py
spikely/elements/guiparams/extractor/__init__.py
spikely/elements/guiparams/extractor/bindatrecordingextractor.py
spikely/elements/guiparams/extractor/biocamrecording.py
spikely/elements/guiparams/extractor/exdirrecording.py
spikely/elements/guiparams/extractor/intanrecordingextractor.py
spikely/elements/guiparams/extractor/klustarecordingextractor.py
spikely/elements/guiparams/extractor/maxonerecording.py
spikely-0.7.2.dist-info/LICENSE
spikely-0.7.2.dist-info/METADATA
spikely-0.7.2.dist-info/WHEEL
spikely-0.7.2.dist-info/entry_points.txt
spikely-0.7.2.dist-info/top_level.txt
spikely-0.7.2.dist-info/RECORD
