Metadata-Version: 2.1
Name: spikely
Version: 0.7.2
Summary: Spike sorting made simple
Home-page: https://github.com/SpikeInterface/spikely
Author: Roger Hurwitz
Author-email: rogerhurwitz@gmail.com
License: UNKNOWN
Platform: UNKNOWN
Classifier: Programming Language :: Python :: 3
Classifier: License :: OSI Approved :: GNU General Public License v3 (GPLv3)
Classifier: Operating System :: OS Independent
Requires-Dist: pyqt5 (>=5.14.2)
Requires-Dist: spikeextractors (>=0.8.4)
Requires-Dist: spikesorters (>=0.3.3)
Requires-Dist: spiketoolkit (>=0.6.3)
